odoo8_addon_l10n_ar_account_check-8.0.1.0.0.99.dev7-py2.7-nspkg.pth
odoo8_addon_l10n_ar_account_check-8.0.1.0.0.99.dev7.dist-info/METADATA
odoo8_addon_l10n_ar_account_check-8.0.1.0.0.99.dev7.dist-info/RECORD
odoo8_addon_l10n_ar_account_check-8.0.1.0.0.99.dev7.dist-info/WHEEL
odoo8_addon_l10n_ar_account_check-8.0.1.0.0.99.dev7.dist-info/namespace_packages.txt
odoo8_addon_l10n_ar_account_check-8.0.1.0.0.99.dev7.dist-info/top_level.txt
odoo_addons/l10n_ar_account_check/.gitignore
odoo_addons/l10n_ar_account_check/AUTHORS
odoo_addons/l10n_ar_account_check/__init__.py
odoo_addons/l10n_ar_account_check/__openerp__.py
odoo_addons/l10n_ar_account_check/account_check.py
odoo_addons/l10n_ar_account_check/account_check_view.xml
odoo_addons/l10n_ar_account_check/account_voucher.py
odoo_addons/l10n_ar_account_check/account_voucher_view.xml
odoo_addons/l10n_ar_account_check/partner_view.xml
odoo_addons/l10n_ar_account_check/res_partner_bank.py
odoo_addons/l10n_ar_account_check/i18n/es_AR-old.po
odoo_addons/l10n_ar_account_check/i18n/es_AR.mo
odoo_addons/l10n_ar_account_check/i18n/es_AR.po
odoo_addons/l10n_ar_account_check/images/treasury-hover.png
odoo_addons/l10n_ar_account_check/images/treasury.png
odoo_addons/l10n_ar_account_check/security/ir.model.access.csv
odoo_addons/l10n_ar_account_check/static/description/icon.png
odoo_addons/l10n_ar_account_check/wizard/__init__.py
odoo_addons/l10n_ar_account_check/wizard/add_checks.py
odoo_addons/l10n_ar_account_check/wizard/add_checks_view.xml
odoo_addons/l10n_ar_account_check/wizard/check_deposit.py
odoo_addons/l10n_ar_account_check/wizard/check_reject.py
odoo_addons/l10n_ar_account_check/wizard/view_check_deposit.xml
odoo_addons/l10n_ar_account_check/wizard/view_check_reject.xml
