Metadata-Version: 2.1
Name: odoo8-addon-l10n-ar-account-check
Version: 8.0.1.0.0.99.dev7
Summary: Account Checks
Home-page: https://github.com/OCA/l10n-argentina
Author: Thymbra/E-MIPS/Eynes,Odoo Community Association (OCA)
Author-email: support@odoo-community.org
License: AGPL-3
Platform: UNKNOWN
Classifier: Programming Language :: Python
Classifier: Framework :: Odoo
Classifier: License :: OSI Approved :: GNU Affero General Public License v3
Requires-Python: ~=2.7
Requires-Dist: odoo8-addon-l10n-ar-account-payment
Requires-Dist: odoo (<9.0a,>=8.0a)
